{
  "required": true,
  "minVersion": "0.8",
  "package": "com.zickzenni.anarchium.mixin",
  "compatibilityLevel": "JAVA_21",
  "mixins": [
    "server.EntityMixin",
    "server.PlayerMixin",
    "server.ServerGamePacketListenerImplMixin"
  ],
  "client": [
    "client.BlockEntityRenderDispatcherMixin",
    "client.CameraMixin",
    "client.EntityRenderDispatcherMixin",
    "client.EntityRendererMixin",
    "client.HumanoidModelMixin",
    "client.KeyboardInputMixin",
    "client.LevelRendererMixin",
    "client.LivingEntityRendererMixin",
    "client.OptionsMixin",
    "client.SoundEngineMixin"
  ],
  "injectors": {
    "defaultRequire": 1
  },
  "overwrites": {
    "requireAnnotations": true
  }
}
